setup.py
HTConsole.egg-info/PKG-INFO
HTConsole.egg-info/SOURCES.txt
HTConsole.egg-info/dependency_links.txt
HTConsole.egg-info/entry_points.txt
HTConsole.egg-info/not-zip-safe
HTConsole.egg-info/paster_plugins.txt
HTConsole.egg-info/requires.txt
HTConsole.egg-info/top_level.txt
docs/devel_config.ini
docs/todo.txt
htconsole/__init__.py
htconsole/command.py
htconsole/evalcontext.py
htconsole/extrabuiltins.py
htconsole/htmlrepr.py
htconsole/sitepage.py
htconsole/wsgiapp.py
htconsole/templates/index.tmpl
htconsole/templates/standard.tmpl
htconsole/web/__init__.py
htconsole/web/index.py
htconsole/web/static/command.js
htconsole/web/static/jstest.html
htconsole/web/static/stylesheet.css
htconsole/web/static/jsdoctest/demo.html
htconsole/web/static/jsdoctest/jsdoctest.js
htconsole/web/static/jsdoctest/MochiKit/MochiKit.js
htconsole/web/static/jsdoctest/MochiKit/__package__.js
htconsole/web/static/mochikit/MochiKit.js
htconsole/web/static/mochikit/__package__.js
tests/conftest.py
tests/test_app.py
